sati/__init__.py
sati/sati.py
sati/socket.py
sati/util.py
sati_ac-0.1.3.dist-info/METADATA
sati_ac-0.1.3.dist-info/WHEEL
sati_ac-0.1.3.dist-info/licenses/LICENSE
sati_ac-0.1.3.dist-info/RECORD
