Metadata-Version: 2.1
Name: sati-ac
Version: 0.1.3
Summary: Next generation anti-captcha
Project-URL: Homepage, https://git.sati.ac/sati.ac/sati-py
Author-email: "sati.ac" <sati.ac@proton.me>
License-File: LICENSE
Classifier: License :: OSI Approved :: MIT License
Classifier: Operating System :: OS Independent
Classifier: Programming Language :: Python :: 3
Requires-Python: >=3.8
Requires-Dist: websockets
